nemzyxt/__init__.py
nemzyxt/hello.py
nemzyxt-1.0.2.dist-info/METADATA
nemzyxt-1.0.2.dist-info/WHEEL
nemzyxt-1.0.2.dist-info/top_level.txt
nemzyxt-1.0.2.dist-info/RECORD
