Metadata-Version: 2.1
Name: nemzyxt
Version: 1.0.2
Summary: My first PyPi package
Author: Nemuel Wainaina
